instruct/__init__.py
instruct/__main__.py
instruct/about.py
instruct/compat.py
instruct/constants.py
instruct/exceptions.py
instruct/lang.py
instruct/subtype.py
instruct/typedef.py
instruct/types.py
instruct/typing.py
instruct/utils.py
instruct/templates/data_class.jinja
instruct/templates/fast_clear.jinja
instruct/templates/fast_dumps.jinja
instruct/templates/fast_eq.jinja
instruct/templates/fast_getitem.jinja
instruct/templates/fast_iter.jinja
instruct/templates/getter.jinja
instruct/templates/history-setter-wrapper.jinja
instruct/templates/macros.jinja
instruct/templates/raw_get_set_state.jinja
instruct/templates/setter.jinja
instruct-0.9.3.dist-info/licenses/LICENSE
instruct-0.9.3.dist-info/METADATA
instruct-0.9.3.dist-info/WHEEL
instruct-0.9.3.dist-info/top_level.txt
instruct-0.9.3.dist-info/RECORD
