Metadata-Version: 2.4
Name: instruct
Version: 0.9.3
Summary: Compact/flexible/fast/strictly-typed class system- similar to Pydantic but focused on ``__slot__``ed objects and ability to support multiple inheritance and type subtraction
Author: Autumn Jolitz
License: BSD-3-Clause
Project-URL: Homepage, https://github.com/autumnjolitz/instruct
Project-URL: Source, https://github.com/autumnjolitz/instruct
Project-URL: Changelog, https://github.com/autumnjolitz/instruct/blob/v0.9.3/CHANGES.rst
Keywords: instruct,typing,mixin,multiple-_inheritance,multiple inheritance,type hints
Classifier: Development Status :: 5 - Production/Stable
Classifier: Environment :: Console
Classifier: Operating System :: Unix
Classifier: Operating System :: POSIX :: Linux
Classifier: Intended Audience :: Developers
Classifier: Programming Language :: Python :: 3 :: Only
Classifier: Programming Language :: Python :: 3.8
Classifier: Programming Language :: Python :: 3.9
Classifier: Programming Language :: Python :: 3.10
Classifier: Programming Language :: Python :: 3.11
Classifier: Programming Language :: Python :: 3.12
Classifier: Topic :: Software Development :: Libraries :: Python Modules
Requires-Python: >=3.7
License-File: LICENSE
Requires-Dist: Jinja2<4.0.0a0,>=3.0.0
Requires-Dist: inflection<1.0.0a0
Requires-Dist: typing-extensions<5.0.0a0,>=4.2.0
Provides-Extra: test
Requires-Dist: pytest; extra == "test"
Requires-Dist: pytest-mock; extra == "test"
Requires-Dist: flake8<5.0.4a0; python_version < "3.8" and extra == "test"
Requires-Dist: flake8>6.0.0; python_version >= "3.8" and extra == "test"
Requires-Dist: pathspec<0.12.0; python_version < "3.8" and extra == "test"
Requires-Dist: pytest-cov; extra == "test"
Requires-Dist: coverage-badge; extra == "test"
Provides-Extra: devel
Requires-Dist: twine; extra == "devel"
Requires-Dist: build; extra == "devel"
Requires-Dist: invoke; extra == "devel"
Requires-Dist: packaging; extra == "devel"
Requires-Dist: pre-commit>=4.1.0; extra == "devel"
Requires-Dist: git-changelog~=2.5.3; extra == "devel"
Requires-Dist: mypy>=1.15.0; python_version >= "3.8" and extra == "devel"
Requires-Dist: pyasyncore; sys_platform == "darwin" and extra == "devel"
Requires-Dist: pyasynchat; sys_platform == "darwin" and extra == "devel"
Dynamic: license-file
